{
	"name": "pipeline3",
	"properties": {
		"activities": [
			{
				"name": "Wait1",
				"type": "Wait",
				"dependsOn": [],
				"userProperties": [],
				"typeProperties": {
					"waitTimeInSeconds": 1
				}
			},
			{
				"name": "Wait2",
				"type": "Wait",
				"dependsOn": [],
				"userProperties": [],
				"typeProperties": {
					"waitTimeInSeconds": 1
				}
			}
		],
		"annotations": [],
		"lastPublishTime": "2022-08-03T16:55:07Z"
	},
	"type": "Microsoft.DataFactory/factories/pipelines"
}